dktshell/__init__.py
dktshell/core.py
dktshell-0.1.2.dist-info/METADATA
dktshell-0.1.2.dist-info/WHEEL
dktshell-0.1.2.dist-info/top_level.txt
dktshell-0.1.2.dist-info/RECORD
