Metadata-Version: 2.4
Name: dktshell
Version: 0.1.2
Summary: Matrix-based structural analysis module for triangulated thin shells
Home-page: https://github.com/kazukihayashi/Matrix-based-shape-sensitivity-analysis-for-linear-strain-energy-of-triangular-thin-shell-elements
Author: Kazuki Hayashi and Romain Mesnil
License: MIT license
Keywords: Discrete Kirchhoff triangle (DKT),Shell,Structural analysis,Finite element analysis (FEM),Finite element method (FEM),Mesh
Requires-Python: >=3.12
Requires-Dist: numpy>=1.26
Requires-Dist: scipy>=1.15
Requires-Dist: numba>=0.61
Dynamic: author
Dynamic: description
Dynamic: description-content-type
Dynamic: home-page
Dynamic: keywords
Dynamic: license
Dynamic: requires-dist
Dynamic: requires-python
Dynamic: summary
